setup.py
segmentation_module/API_test.py
segmentation_module/__init__.py
segmentation_module/segmentation_api/API.py
segmentation_module/segmentation_api/API_deprecated.py
segmentation_module/segmentation_api/__init__.py
segmentation_module/segmentation_api/api_object.py
segmentation_module/segmentation_api/evaluator.py
segmentation_module/segmentation_api/logger.py
segmentation_module/segmentation_api/predictor.py
segmentation_module/segmentation_api/trainer.py
segmentation_module/segmentation_api/visualizator.py
segmentation_module/segmentation_models/BilinearUpSampling.py
segmentation_module/segmentation_models/__init__.py
segmentation_module/segmentation_models/fcn.py
segmentation_module/segmentation_models/pspnet.py
segmentation_module/segmentation_models/unet.py
segmentation_module/segmentation_support/__init__.py
segmentation_module/segmentation_support/csv_preparing.py
segmentation_module/segmentation_support/h5_creator.py
segmentation_module/segmentation_tools/__init__.py
segmentation_module/segmentation_tools/eval_tools.py
segmentation_module/segmentation_tools/generator.py
segmentation_module/segmentation_tools/generator_tools.py
segmentation_module/segmentation_tools/segmentation_tools.py
segmentation_module/segmentation_tools/utils2.py
segmentation_package.egg-info/PKG-INFO
segmentation_package.egg-info/SOURCES.txt
segmentation_package.egg-info/dependency_links.txt
segmentation_package.egg-info/requires.txt
segmentation_package.egg-info/top_level.txt