Metadata-Version: 2.1
Name: segmentation_package
Version: 0.2
Summary: Tool for segmentation sattelite images.
Home-page: https://github.com/me/myproject
Author: PR&MG
Author-email: asd@gmail.com
License: MIT
Platform: UNKNOWN
Classifier: License :: OSI Approved :: MIT License
Classifier: Programming Language :: Python
Classifier: Programming Language :: Python :: 3
Classifier: Programming Language :: Python :: 3.6
Classifier: Programming Language :: Python :: Implementation :: CPython
Classifier: Programming Language :: Python :: Implementation :: PyPy
Requires-Python: >=3.6.0
